{
  "current_batch": 1,
  "current_step": "execute",
  "model_assignments": {
    "executor": {"model": "{{EXECUTOR_MODEL}}", "effort": "{{EXECUTOR_EFFORT}}", "agent": "orchestrator-executor"},
    "reviewer": {"model": "{{REVIEWER_MODEL}}", "effort": "{{REVIEWER_EFFORT}}", "agent": "orchestrator-reviewer"},
    "qa":       {"model": "{{QA_MODEL}}",       "effort": "{{QA_EFFORT}}",       "agent": "orchestrator-qa"}
  },
  "step_detail": "Ready to begin Batch 1 execution.",
  "batches_completed": [],
  "batches_in_progress": null,
  "qa_status": null,
  "audit_status": null,
  "audit_attempts": 0,
  "last_updated": "{{TIMESTAMP}}",
  "notes": "Orchestrator initialized from plan."
}
